rstapi/__init__.py
rstapi/api.py
rstapi/ioclookup.py
rstapi/noisecontrol.py
rstapi/reporthub.py
rstapi/threatfeed.py
rstapi/whoisapi.py
rstapi-1.0.4.dist-info/LICENSE
rstapi-1.0.4.dist-info/METADATA
rstapi-1.0.4.dist-info/WHEEL
rstapi-1.0.4.dist-info/top_level.txt
rstapi-1.0.4.dist-info/RECORD
