Metadata-Version: 2.1
Name: rstapi
Version: 1.0.4
Summary: Python library to access the RST Cloud API.
Home-page: https://github.com/rstcloud/rstapi-python
Author: RST Cloud Pty Ltd
Author-email: support@rstcloud.net, ysergeev@rstcloud.net
License: MIT
Keywords: threat intelligence,RST Cloud,IoC lookup,Whois API
Classifier: Development Status :: 5 - Production/Stable
Classifier: License :: OSI Approved :: MIT License
Classifier: Operating System :: OS Independent
Classifier: Topic :: Security
Classifier: Programming Language :: Python :: 3
License-File: LICENSE
Requires-Dist: requests
